veman/__init__.py
veman/__main__.py
veman/_version.py
veman/main.py
veman-0.3.0.dist-info/LICENSE
veman-0.3.0.dist-info/METADATA
veman-0.3.0.dist-info/WHEEL
veman-0.3.0.dist-info/entry_points.txt
veman-0.3.0.dist-info/top_level.txt
veman-0.3.0.dist-info/RECORD
