Metadata-Version: 2.1
Name: veman
Version: 0.3.0
Summary: Virtual environment manager for venv
Author: Mikael Tranbom
Author-email: mikael@tranbom.io
License: GPLv3
Project-URL: Homepage, https://tranbom.io/veman/
Project-URL: Repository, https://gitlab.com/tranbom/veman
Project-URL: Documentation, https://tranbom.io/veman/
Keywords: venv,virtual environment,utility,developer tools,virtual environment manager
Classifier: Development Status :: 5 - Production/Stable
Classifier: Environment :: Console
Classifier: Intended Audience :: Developers
Classifier: License :: OSI Approved :: GNU General Public License v3 (GPLv3)
Classifier: Natural Language :: English
Classifier: Operating System :: MacOS
Classifier: Operating System :: MacOS :: MacOS X
Classifier: Operating System :: POSIX :: BSD :: FreeBSD
Classifier: Operating System :: POSIX :: Linux
Classifier: Programming Language :: Python
Classifier: Programming Language :: Python :: 3
Classifier: Programming Language :: Python :: 3.9
Classifier: Programming Language :: Python :: 3.10
Classifier: Programming Language :: Python :: 3.11
Classifier: Programming Language :: Python :: 3.12
Classifier: Topic :: Software Development
Classifier: Topic :: Utilities
Requires-Python: >=3.9
License-File: LICENSE
